cogent3/__init__.py
cogent3/_plugin.py
cogent3/_version.py
cogent3/py.typed
cogent3/_dataset/__init__.py
cogent3/_dataset/brca1.fasta
cogent3/_dataset/murphy.tree
cogent3/align/__init__.py
cogent3/align/align.py
cogent3/align/dp_calculation.py
cogent3/align/indel_model.py
cogent3/align/indel_positions.py
cogent3/align/pairwise.py
cogent3/align/pairwise_pogs_numba.py
cogent3/align/pairwise_seqs_numba.py
cogent3/align/progressive.py
cogent3/align/pycompare.py
cogent3/align/traceback.py
cogent3/app/__init__.py
cogent3/app/align.py
cogent3/app/composable.py
cogent3/app/data_store.py
cogent3/app/dist.py
cogent3/app/evo.py
cogent3/app/io.py
cogent3/app/result.py
cogent3/app/sample.py
cogent3/app/sqlite_data_store.py
cogent3/app/translate.py
cogent3/app/tree.py
cogent3/app/typing.py
cogent3/cluster/UPGMA.py
cogent3/cluster/__init__.py
cogent3/core/__init__.py
cogent3/core/alignment.py
cogent3/core/alphabet.py
cogent3/core/annotation.py
cogent3/core/annotation_db.py
cogent3/core/genetic_code.py
cogent3/core/info.py
cogent3/core/location.py
cogent3/core/moltype.py
cogent3/core/profile.py
cogent3/core/seq_storage.py
cogent3/core/sequence.py
cogent3/core/seqview.py
cogent3/core/slice_record.py
cogent3/core/table.py
cogent3/core/tree.py
cogent3/data/__init__.py
cogent3/data/energy_params.py
cogent3/data/molecular_weight.py
cogent3/draw/__init__.py
cogent3/draw/dendrogram.py
cogent3/draw/dotplot.py
cogent3/draw/drawable.py
cogent3/draw/letter.py
cogent3/draw/logo.py
cogent3/evolve/__init__.py
cogent3/evolve/best_likelihood.py
cogent3/evolve/bootstrap.py
cogent3/evolve/coevolution.py
cogent3/evolve/discrete_markov.py
cogent3/evolve/distance.py
cogent3/evolve/fast_distance.py
cogent3/evolve/likelihood_calculation.py
cogent3/evolve/likelihood_function.py
cogent3/evolve/likelihood_tree.py
cogent3/evolve/likelihood_tree_numba.py
cogent3/evolve/models.py
cogent3/evolve/motif_prob_model.py
cogent3/evolve/ns_substitution_model.py
cogent3/evolve/pairwise_distance_numba.py
cogent3-2026.1.20a1.dist-info/entry_points.txt
cogent3-2026.1.20a1.dist-info/licenses/LICENSE
cogent3-2026.1.20a1.dist-info/WHEEL
cogent3-2026.1.20a1.dist-info/METADATA
cogent3-2026.1.20a1.dist-info/RECORD
