Metadata-Version: 2.4
Name: cogent3
Version: 2026.1.20a1
Summary: COmparative GENomics Toolkit 3: genomic sequence analysis within notebooks or on compute systems with 1000s of CPUs.
Keywords: biology,genomics,statistics,phylogeny,evolution,bioinformatics
Author-email: Gavin Huttley <Gavin.Huttley@anu.edu.au>
Requires-Python: >=3.11,<3.15
Classifier: Development Status :: 5 - Production/Stable
Classifier: Intended Audience :: Science/Research
Classifier: License :: OSI Approved :: BSD License
Classifier: Topic :: Scientific/Engineering :: Bio-Informatics
Classifier: Topic :: Software Development :: Libraries :: Python Modules
Classifier: Operating System :: OS Independent
Classifier: Programming Language :: Python :: 3.11
Classifier: Programming Language :: Python :: 3.12
Classifier: Programming Language :: Python :: 3.13
Classifier: Programming Language :: Python :: 3.14
License-File: LICENSE
Requires-Dist: charset_normalizer
Requires-Dist: loky!=3.5.0
Requires-Dist: numpy<2.5
Requires-Dist: numba>=0.57.0; python_version=='3.11'
Requires-Dist: numba>=0.59.0; python_version=='3.12'
Requires-Dist: numba>=0.61.0; python_version=='3.13'
Requires-Dist: numba>=0.63.0rc1; python_version=='3.14'
Requires-Dist: scipy
Requires-Dist: scitrack
Requires-Dist: stevedore
Requires-Dist: tqdm
Requires-Dist: typing_extensions
Requires-Dist: flit ; extra == "dev"
Requires-Dist: nox ; extra == "dev"
Requires-Dist: numpydoc ; extra == "dev"
Requires-Dist: scriv ; extra == "dev"
Requires-Dist: types-tqdm ; extra == "dev"
Requires-Dist: cogent3[doc] ; extra == "dev"
Requires-Dist: cogent3[test] ; extra == "dev"
Requires-Dist: cogent3[typing] ; extra == "dev"
Requires-Dist: click ; extra == "doc"
Requires-Dist: cogent3[extra] ; extra == "doc"
Requires-Dist: cogent3-h5seqs>=0.7.3 ; extra == "doc"
Requires-Dist: jupyter-sphinx ; extra == "doc"
Requires-Dist: jupyter_client ; extra == "doc"
Requires-Dist: jupytext ; extra == "doc"
Requires-Dist: nbconvert>5.4 ; extra == "doc"
Requires-Dist: nbformat ; extra == "doc"
Requires-Dist: nbsphinx ; extra == "doc"
Requires-Dist: numpydoc ; extra == "doc"
Requires-Dist: piqtree>=0.8.0 ; extra == "doc" and ( python_version > '3.11')
Requires-Dist: sphinx ; extra == "doc"
Requires-Dist: sphinx-autobuild ; extra == "doc"
Requires-Dist: pydata_sphinx_theme ; extra == "doc"
Requires-Dist: sphinx_design ; extra == "doc"
Requires-Dist: sphinxcontrib-bibtex ; extra == "doc"
Requires-Dist: sphinxcontrib-video ; extra == "doc"
Requires-Dist: iplotx>=0.6.8 ; extra == "doc"
Requires-Dist: ipykernel ; extra == "extra"
Requires-Dist: ipython ; extra == "extra"
Requires-Dist: ipywidgets ; extra == "extra"
Requires-Dist: jupyterlab ; extra == "extra"
Requires-Dist: kaleido ; extra == "extra"
Requires-Dist: notebook ; extra == "extra"
Requires-Dist: pandas ; extra == "extra"
Requires-Dist: pillow ; extra == "extra"
Requires-Dist: plotly ; extra == "extra"
Requires-Dist: psutil ; extra == "extra"
Requires-Dist: cogent3-h5seqs>=0.7.3 ; extra == "test"
Requires-Dist: piqtree>=0.8.0 ; extra == "test" and ( python_version > '3.11')
Requires-Dist: ruff==0.14.13 ; extra == "test"
Requires-Dist: kaleido ; extra == "test"
Requires-Dist: pandas ; extra == "test"
Requires-Dist: plotly ; extra == "test"
Requires-Dist: psutil ; extra == "test"
Requires-Dist: pytest ; extra == "test"
Requires-Dist: pytest-cov ; extra == "test"
Requires-Dist: pytest-xdist ; extra == "test"
Requires-Dist: nox ; extra == "test"
Requires-Dist: mypy==1.19.1 ; extra == "typing"
Project-URL: Bug Tracker, https://github.com/cogent3/cogent3/issues
Project-URL: Changelog, https://github.com/cogent3/cogent3/blob/develop/changelog.md
Project-URL: Documentation, https://www.cogent3.org/
Project-URL: Source Code, https://github.com/cogent3/cogent3
Provides-Extra: dev
Provides-Extra: doc
Provides-Extra: extra
Provides-Extra: test
Provides-Extra: typing
